ELRM/ELRM.py
ELRM/__init__.py
ELRM-1.0.dist-info/LICENSE.txt
ELRM-1.0.dist-info/METADATA
ELRM-1.0.dist-info/WHEEL
ELRM-1.0.dist-info/top_level.txt
ELRM-1.0.dist-info/RECORD
