Metadata-Version: 2.1
Name: ELRM
Version: 1.0
Summary: UNKNOWN
Home-page: UNKNOWN
Author: StudyUp9
Author-email: chengcheng.study@gmail.com
License: UNKNOWN
Platform: UNKNOWN
Classifier: Programming Language :: Python :: 3
Classifier: License :: OSI Approved :: MIT License
Classifier: Operating System :: OS Independent
Requires-Python: >=3
License-File: LICENSE.txt
Requires-Dist: pillow
